pyclicker/__init__.py
pyclicker/cli.py
pyclicker-1.0.0.dist-info/METADATA
pyclicker-1.0.0.dist-info/WHEEL
pyclicker-1.0.0.dist-info/entry_points.txt
pyclicker-1.0.0.dist-info/top_level.txt
pyclicker-1.0.0.dist-info/RECORD
